transaction_utils/__init__.py
transaction_utils/modules.py
transactions/__init__.py
transactions/modules.py
transaction_utils-0.1.1.dist-info/LICENSE
transaction_utils-0.1.1.dist-info/METADATA
transaction_utils-0.1.1.dist-info/WHEEL
transaction_utils-0.1.1.dist-info/top_level.txt
transaction_utils-0.1.1.dist-info/RECORD
