Metadata-Version: 2.2
Name: transaction_utils
Version: 0.1.1
Classifier: Programming Language :: Python :: 3
Classifier: License :: OSI Approved :: MIT License
Classifier: Operating System :: OS Independent
Requires-Python: >=3.6
License-File: LICENSE
Requires-Dist: base58>=2.0.0
Requires-Dist: solders>=0.23.0
Requires-Dist: requests>=2.20.0
Dynamic: classifier
Dynamic: requires-dist
Dynamic: requires-python
